{"para": [{"component": "paragraph", "lines": [{"bbox": [75, 147, 1422, 177], "words": [{"bbox": [75, 149, 123, 172], "text": "Gi\u1ea3i"}, {"bbox": [131, 152, 191, 177], "text": "b\u00f3ng"}, {"bbox": [199, 152, 229, 172], "text": "\u0111\u00e1"}, {"bbox": [237, 152, 297, 177], "text": "h\u1ea1ng"}, {"bbox": [305, 147, 358, 172], "text": "nh\u1ea5t"}, {"bbox": [366, 147, 425, 177], "text": "qu\u1ed1c"}, {"bbox": [433, 152, 469, 177], "text": "gia"}, {"bbox": [477, 152, 545, 176], "text": "2013,"}, {"bbox": [553, 152, 603, 172], "text": "Hoa"}, {"bbox": [611, 152, 643, 177], "text": "K\u1ef3"}, {"bbox": [651, 152, 720, 172], "text": "1971-"}, {"bbox": [728, 152, 805, 177], "text": "Ng\u01b0\u1eddi"}, {"bbox": [813, 152, 846, 172], "text": "Ba"}, {"bbox": [854, 152, 899, 172], "text": "Lan"}, {"bbox": [907, 152, 936, 176], "text": "t\u1ea1i"}, {"bbox": [943, 152, 992, 172], "text": "Anh"}, {"bbox": [1000, 152, 1083, 177], "text": "T\u01b0\u01a1ng"}, {"bbox": [1091, 152, 1128, 172], "text": "t\u00e1c"}, {"bbox": [1136, 147, 1181, 177], "text": "h\u1ea5p"}, {"bbox": [1189, 148, 1234, 172], "text": "d\u1eabn"}, {"bbox": [1242, 152, 1299, 172], "text": "N\u0103m"}, {"bbox": [1307, 152, 1376, 177], "text": "B\u00f3ngi"}, {"bbox": [1384, 152, 1422, 172], "text": "\u0111\u00e1."}], "texts": ["Gi\u1ea3i", "b\u00f3ng", "\u0111\u00e1", "h\u1ea1ng", "nh\u1ea5t", "qu\u1ed1c", "gia", "2013,", "Hoa", "K\u1ef3", "1971-", "Ng\u01b0\u1eddi", "Ba", "Lan", "t\u1ea1i", "Anh", "T\u01b0\u01a1ng", "t\u00e1c", "h\u1ea5p", "d\u1eabn", "N\u0103m", "B\u00f3ngi", "\u0111\u00e1."]}, {"bbox": [75, 179, 1420, 209], "words": [{"bbox": [75, 184, 220, 209], "text": "Nottinghami"}, {"bbox": [228, 184, 322, 204], "text": "Forest!."}, {"bbox": [330, 184, 383, 204], "text": "F.C."}, {"bbox": [390, 179, 431, 204], "text": "H\u1ed3i"}, {"bbox": [439, 184, 490, 209], "text": "gi\u00e1o"}, {"bbox": [498, 184, 573, 209], "text": "Tokyo"}, {"bbox": [581, 184, 634, 209], "text": "Ti\u1ec7p"}, {"bbox": [642, 179, 704, 204], "text": "Kh\u1eafc"}, {"bbox": [712, 184, 741, 208], "text": "t\u1ea1i"}, {"bbox": [749, 179, 796, 204], "text": "Th\u1ebf"}, {"bbox": [804, 184, 848, 208], "text": "v\u1eadn"}, {"bbox": [856, 184, 892, 208], "text": "h\u1ed9i"}, {"bbox": [900, 184, 952, 204], "text": "M\u00f9a"}, {"bbox": [960, 184, 990, 204], "text": "h\u00e8"}, {"bbox": [998, 184, 1058, 204], "text": "1936"}, {"bbox": [1066, 184, 1155, 209], "text": "T\u01b0\u01a1ngi"}, {"bbox": [1163, 184, 1200, 204], "text": "t\u00e1c"}, {"bbox": [1208, 179, 1253, 209], "text": "h\u1ea5p"}, {"bbox": [1261, 180, 1306, 204], "text": "d\u1eabn"}, {"bbox": [1314, 184, 1393, 209], "text": "Lloyds"}, {"bbox": [1401, 184, 1419, 204], "text": "B"}], "texts": ["Nottinghami", "Forest!.", "F.C.", "H\u1ed3i", "gi\u00e1o", "Tokyo", "Ti\u1ec7p", "Kh\u1eafc", "t\u1ea1i", "Th\u1ebf", "v\u1eadn", "h\u1ed9i", "M\u00f9a", "h\u00e8", "1936", "T\u01b0\u01a1ngi", "t\u00e1c", "h\u1ea5p", "d\u1eabn", "Lloyds", "B"]}, {"bbox": [75, 211, 1412, 241], "words": [{"bbox": [75, 216, 181, 236], "text": "Scotland"}, {"bbox": [189, 216, 249, 236], "text": "1955"}, {"bbox": [256, 216, 366, 236], "text": "Abraham"}, {"bbox": [374, 216, 460, 236], "text": "Lincoln"}, {"bbox": [468, 216, 557, 236], "text": "19181l."}, {"bbox": [565, 216, 666, 236], "text": "Yahoo!?"}, {"bbox": [673, 216, 721, 236], "text": "S\u00e2n"}, {"bbox": [729, 216, 773, 241], "text": "bay"}, {"bbox": [781, 211, 840, 241], "text": "qu\u1ed1c"}, {"bbox": [848, 211, 871, 236], "text": "t\u1ebf"}, {"bbox": [879, 216, 920, 240], "text": "N\u1ed9i"}, {"bbox": [928, 216, 982, 236], "text": "B\u00e0i?"}, {"bbox": [990, 216, 1064, 236], "text": "Belize"}, {"bbox": [1072, 216, 1101, 240], "text": "t\u1ea1i"}, {"bbox": [1109, 211, 1156, 236], "text": "Th\u1ebf"}, {"bbox": [1164, 216, 1216, 240], "text": "v\u1eadn!"}, {"bbox": [1224, 216, 1260, 240], "text": "h\u1ed9i"}, {"bbox": [1268, 216, 1320, 236], "text": "M\u00f9a"}, {"bbox": [1328, 216, 1358, 236], "text": "h\u00e8"}, {"bbox": [1366, 216, 1411, 236], "text": "201"}], "texts": ["Scotland", "1955", "Abraham", "Lincoln", "19181l.", "Yahoo!?", "S\u00e2n", "bay", "qu\u1ed1c", "t\u1ebf", "N\u1ed9i", "B\u00e0i?", "Belize", "t\u1ea1i", "Th\u1ebf", "v\u1eadn!", "h\u1ed9i", "M\u00f9a", "h\u00e8", "201"]}, {"bbox": [75, 242, 1424, 274], "words": [{"bbox": [75, 249, 203, 269], "text": "Katsusuke"}, {"bbox": [211, 249, 359, 274], "text": "Yanagisawa"}, {"bbox": [366, 249, 423, 269], "text": "Gi\u00e0u"}, {"bbox": [431, 249, 461, 269], "text": "24"}, {"bbox": [469, 249, 537, 274], "text": "th\u00e1ng"}, {"bbox": [545, 249, 560, 269], "text": "3"}, {"bbox": [568, 242, 622, 269], "text": "Bi\u1ec3n"}, {"bbox": [630, 249, 810, 269], "text": "Cosmonauts\u2014"}, {"bbox": [818, 249, 949, 274], "text": "Circulatory"}, {"bbox": [957, 249, 1044, 274], "text": "system"}, {"bbox": [1052, 249, 1188, 274], "text": "Carthago;!:"}, {"bbox": [1196, 249, 1302, 273], "text": "Mattoon,"}, {"bbox": [1310, 249, 1394, 269], "text": "Illinois:"}, {"bbox": [1402, 249, 1423, 271], "text": "Q"}], "texts": ["Katsusuke", "Yanagisawa", "Gi\u00e0u", "24", "th\u00e1ng", "3", "Bi\u1ec3n", "Cosmonauts\u2014", "Circulatory", "system", "Carthago;!:", "Mattoon,", "Illinois:", "Q"]}, {"bbox": [75, 278, 1420, 306], "words": [{"bbox": [75, 281, 123, 301], "text": "Ph\u00f9"}, {"bbox": [131, 281, 187, 305], "text": "L\u01b0u,"}, {"bbox": [195, 281, 239, 305], "text": "L\u1ed9c"}, {"bbox": [247, 281, 282, 301], "text": "H\u00e0"}, {"bbox": [290, 281, 366, 301], "text": "KevinI"}, {"bbox": [374, 281, 442, 301], "text": "th\u00e0nh"}, {"bbox": [450, 281, 603, 306], "text": "Glendalough"}, {"bbox": [611, 281, 671, 301], "text": "1972"}, {"bbox": [679, 281, 734, 301], "text": "C\u00e1ci"}, {"bbox": [742, 281, 786, 301], "text": "khu"}, {"bbox": [794, 281, 868, 306], "text": "ngo\u1ea1iI"}, {"bbox": [876, 281, 896, 301], "text": "vi"}, {"bbox": [904, 281, 938, 306], "text": "Hy"}, {"bbox": [946, 281, 999, 306], "text": "L\u1ea1p;"}, {"bbox": [1006, 281, 1048, 305], "text": "\u0110\u1ecba"}, {"bbox": [1056, 281, 1127, 306], "text": "Trung"}, {"bbox": [1134, 278, 1175, 301], "text": "H\u1ea3i"}, {"bbox": [1183, 281, 1243, 301], "text": "1992"}, {"bbox": [1250, 281, 1323, 301], "text": "Arena"}, {"bbox": [1331, 281, 1419, 301], "text": "football"}], "texts": ["Ph\u00f9", "L\u01b0u,", "L\u1ed9c", "H\u00e0", "KevinI", "th\u00e0nh", "Glendalough", "1972", "C\u00e1ci", "khu", "ngo\u1ea1iI", "vi", "Hy", "L\u1ea1p;", "\u0110\u1ecba", "Trung", "H\u1ea3i", "1992", "Arena", "football"]}, {"bbox": [75, 307, 1416, 339], "words": [{"bbox": [75, 307, 117, 339], "text": "\u1ee6y;"}, {"bbox": [125, 314, 170, 334], "text": "ban"}, {"bbox": [178, 314, 266, 334], "text": "Malfatti"}, {"bbox": [274, 314, 322, 334], "text": "IBM"}, {"bbox": [330, 314, 405, 339], "text": "Tokyo"}, {"bbox": [412, 314, 529, 334], "text": "Research"}, {"bbox": [537, 314, 667, 339], "text": "Laboratory"}, {"bbox": [675, 309, 722, 334], "text": "B\u1eafc"}, {"bbox": [730, 314, 766, 339], "text": "M\u1ef9"}, {"bbox": [774, 314, 841, 338], "text": "thu\u1ed9c"}, {"bbox": [849, 314, 908, 339], "text": "v\u00f9ng"}, {"bbox": [916, 309, 963, 334], "text": "B\u1eafc"}, {"bbox": [971, 314, 1023, 338], "text": "C\u1ef1c"}, {"bbox": [1031, 314, 1086, 334], "text": "T\u00ednh"}, {"bbox": [1094, 314, 1124, 334], "text": "\u0111a"}, {"bbox": [1132, 309, 1175, 334], "text": "s\u1eafc"}, {"bbox": [1182, 309, 1218, 334], "text": "\u0110\u1ebf"}, {"bbox": [1226, 309, 1285, 339], "text": "qu\u1ed1c"}, {"bbox": [1293, 314, 1329, 334], "text": "Lai"}, {"bbox": [1337, 314, 1374, 334], "text": "M\u00e3"}, {"bbox": [1382, 314, 1415, 338], "text": "B\u1ed9"}], "texts": ["\u1ee6y;", "ban", "Malfatti", "IBM", "Tokyo", "Research", "Laboratory", "B\u1eafc", "M\u1ef9", "thu\u1ed9c", "v\u00f9ng", "B\u1eafc", "C\u1ef1c", "T\u00ednh", "\u0111a", "s\u1eafc", "\u0110\u1ebf", "qu\u1ed1c", "Lai", "M\u00e3", "B\u1ed9"]}, {"bbox": [75, 339, 1422, 371], "words": [{"bbox": [75, 346, 222, 366], "text": "VietNamNet"}, {"bbox": [230, 346, 273, 366], "text": "UL:"}, {"bbox": [281, 346, 341, 366], "text": "1748"}, {"bbox": [349, 346, 485, 366], "text": "Momotarou"}, {"bbox": [493, 351, 523, 366], "text": "no"}, {"bbox": [531, 346, 649, 366], "text": "Umiwashi"}, {"bbox": [657, 346, 707, 366], "text": "Cao"}, {"bbox": [715, 346, 775, 366], "text": "L\u00e3nh"}, {"bbox": [783, 346, 834, 366], "text": "S\u01a1n"}, {"bbox": [842, 346, 872, 366], "text": "La"}, {"bbox": [880, 346, 957, 371], "text": "(th\u00e0nh"}, {"bbox": [965, 341, 1019, 371], "text": "ph\u1ed1)"}, {"bbox": [1027, 346, 1057, 366], "text": "26"}, {"bbox": [1065, 346, 1133, 371], "text": "th\u00e1ng"}, {"bbox": [1141, 346, 1179, 366], "text": "10!"}, {"bbox": [1187, 346, 1250, 371], "text": "B\u00f3ng"}, {"bbox": [1258, 346, 1288, 366], "text": "\u0111\u00e1"}, {"bbox": [1296, 346, 1332, 366], "text": "b\u00e3i"}, {"bbox": [1340, 339, 1399, 370], "text": "bi\u1ec3n;"}, {"bbox": [1407, 346, 1422, 366], "text": "L"}], "texts": ["VietNamNet", "UL:", "1748", "Momotarou", "no", "Umiwashi", "Cao", "L\u00e3nh", "S\u01a1n", "La", "(th\u00e0nh", "ph\u1ed1)", "26", "th\u00e1ng", "10!", "B\u00f3ng", "\u0111\u00e1", "b\u00e3i", "bi\u1ec3n;", "L"]}, {"bbox": [75, 374, 1420, 404], "words": [{"bbox": [75, 374, 137, 399], "text": "Tu\u1ea7n"}, {"bbox": [144, 379, 231, 404], "text": "d\u01b0\u01a1ngi"}, {"bbox": [239, 379, 299, 403], "text": "h\u1ea1m:"}, {"bbox": [307, 379, 365, 403], "text": "Nh\u1eadt"}, {"bbox": [373, 376, 421, 399], "text": "B\u1ea3n"}, {"bbox": [428, 379, 519, 399], "text": "Akashi!"}, {"bbox": [526, 374, 568, 399], "text": "\u0110\u1ed1i"}, {"bbox": [576, 379, 634, 399], "text": "c\u00e1ch"}, {"bbox": [642, 379, 702, 399], "text": "1886"}, {"bbox": [710, 379, 728, 399], "text": "Y"}, {"bbox": [736, 379, 765, 404], "text": "Ly"}, {"bbox": [773, 379, 814, 399], "text": "Ni\u00ea"}, {"bbox": [822, 379, 892, 399], "text": "Kd\u0103m"}, {"bbox": [900, 374, 948, 399], "text": "B\u1ed3n"}, {"bbox": [956, 379, 992, 403], "text": "\u0111\u1ecba"}, {"bbox": [999, 379, 1041, 403], "text": "\u0110\u1ecba"}, {"bbox": [1049, 379, 1120, 404], "text": "Trung"}, {"bbox": [1128, 376, 1177, 399], "text": "H\u1ea3i!"}, {"bbox": [1185, 376, 1233, 399], "text": "Gi\u1ea3i"}, {"bbox": [1241, 379, 1301, 404], "text": "b\u00f3ng"}, {"bbox": [1309, 379, 1339, 399], "text": "\u0111\u00e1"}, {"bbox": [1347, 379, 1376, 399], "text": "v\u00f4"}, {"bbox": [1384, 379, 1419, 403], "text": "\u0111\u1ecbc"}], "texts": ["Tu\u1ea7n", "d\u01b0\u01a1ngi", "h\u1ea1m:", "Nh\u1eadt", "B\u1ea3n", "Akashi!", "\u0110\u1ed1i", "c\u00e1ch", "1886", "Y", "Ly", "Ni\u00ea", "Kd\u0103m", "B\u1ed3n", "\u0111\u1ecba", "\u0110\u1ecba", "Trung", "H\u1ea3i!", "Gi\u1ea3i", "b\u00f3ng", "\u0111\u00e1", "v\u00f4", "\u0111\u1ecbc"]}, {"bbox": [75, 411, 277, 436], "words": [{"bbox": [75, 411, 177, 431], "text": "Master's"}, {"bbox": [185, 411, 277, 436], "text": "degree."}], "texts": ["Master's degree"]}], "bbox": [75, 147, 1425, 439]}, {"component": "paragraph", "lines": [{"bbox": [75, 441, 1420, 473], "words": [{"bbox": [75, 448, 176, 473], "text": "Ch\u01b0\u01a1ng"}, {"bbox": [184, 448, 235, 472], "text": "M\u1ee5c"}, {"bbox": [243, 448, 318, 473], "text": "ho\u00e0ng"}, {"bbox": [326, 448, 371, 472], "text": "h\u1eadu"}, {"bbox": [379, 448, 449, 468], "text": "World"}, {"bbox": [457, 448, 507, 473], "text": "Cup"}, {"bbox": [515, 448, 575, 468], "text": "1974"}, {"bbox": [582, 448, 607, 468], "text": "Al"}, {"bbox": [614, 448, 654, 468], "text": "Ain"}, {"bbox": [662, 441, 716, 468], "text": "Bi\u1ec3n"}, {"bbox": [724, 448, 778, 473], "text": "King"}, {"bbox": [786, 448, 880, 468], "text": "Haakon"}, {"bbox": [888, 448, 930, 468], "text": "VII!"}, {"bbox": [938, 448, 1039, 468], "text": "Portable"}, {"bbox": [1047, 448, 1120, 468], "text": "Media"}, {"bbox": [1128, 448, 1211, 468], "text": "Center"}, {"bbox": [1218, 448, 1281, 472], "text": "B\u1ec7nh"}, {"bbox": [1289, 448, 1333, 468], "text": "ti\u00eau"}, {"bbox": [1341, 448, 1394, 468], "text": "h\u00f3a!"}, {"bbox": [1402, 448, 1420, 468], "text": "S"}], "texts": ["Ch\u01b0\u01a1ng", "M\u1ee5c", "ho\u00e0ng", "h\u1eadu", "World", "Cup", "1974", "Al", "Ain", "Bi\u1ec3n", "King", "Haakon", "VII!", "Portable", "Media", "Center", "B\u1ec7nh", "ti\u00eau", "h\u00f3a!", "S"]}, {"bbox": [75, 479, 1413, 504], "words": [{"bbox": [75, 479, 140, 504], "text": "C\u00e0ng"}, {"bbox": [148, 479, 216, 504], "text": "Long,"}, {"bbox": [224, 479, 286, 504], "text": "Sony"}, {"bbox": [294, 479, 377, 499], "text": "Namiki"}, {"bbox": [385, 479, 471, 504], "text": "Senry\u016b"}, {"bbox": [479, 479, 487, 499], "text": "I"}, {"bbox": [495, 479, 585, 499], "text": "London"}, {"bbox": [593, 479, 687, 504], "text": "Heliport"}, {"bbox": [695, 479, 751, 504], "text": "Hi\u1ec7p"}, {"bbox": [759, 479, 824, 499], "text": "\u01b0\u1edbc1"}, {"bbox": [832, 479, 1004, 504], "text": "Ph\u00e1p-Armenia"}, {"bbox": [1012, 479, 1090, 504], "text": "(1916)"}, {"bbox": [1098, 479, 1148, 504], "text": "C\u00fap"}, {"bbox": [1156, 479, 1207, 499], "text": "Li\u00ean"}, {"bbox": [1215, 479, 1275, 499], "text": "\u0111o\u00e0n"}, {"bbox": [1283, 479, 1332, 499], "text": "c\u00e1cl"}, {"bbox": [1340, 479, 1399, 499], "text": "ch\u00e2u"}, {"bbox": [1407, 479, 1413, 499], "text": "l"}], "texts": ["C\u00e0ng", "Long,", "Sony", "Namiki", "Senry\u016b", "I", "London", "Heliport", "Hi\u1ec7p", "\u01b0\u1edbc1", "Ph\u00e1p-Armenia", "(1916)", "C\u00fap", "Li\u00ean", "\u0111o\u00e0n", "c\u00e1cl", "ch\u00e2u", "l"]}, {"bbox": [75, 508, 1416, 536], "words": [{"bbox": [75, 511, 104, 536], "text": "L\u00fd"}, {"bbox": [112, 511, 185, 536], "text": "Ngh\u0129a"}, {"bbox": [193, 508, 241, 531], "text": "Ph\u1ee7"}, {"bbox": [249, 511, 366, 531], "text": "Mondelez"}, {"bbox": [374, 511, 533, 531], "text": "International-"}, {"bbox": [541, 511, 600, 531], "text": "IosifI"}, {"bbox": [608, 511, 784, 531], "text": "Vissarionovich"}, {"bbox": [792, 511, 860, 531], "text": "Stalin"}, {"bbox": [868, 511, 918, 531], "text": "Cha"}, {"bbox": [926, 516, 978, 531], "text": "con."}, {"bbox": [986, 511, 1037, 531], "text": "nh\u00e0i"}, {"bbox": [1045, 511, 1190, 536], "text": "Stephenson"}, {"bbox": [1198, 511, 1233, 535], "text": "H\u1ec7"}, {"bbox": [1241, 511, 1301, 531], "text": "th\u00edch"}, {"bbox": [1309, 511, 1360, 536], "text": "nghi"}, {"bbox": [1368, 511, 1416, 535], "text": "d\u1ef1a"}], "texts": ["L\u00fd", "Ngh\u0129a", "Ph\u1ee7", "Mondelez", "International-", "IosifI", "Vissarionovich", "Stalin", "Cha", "con.", "nh\u00e0i", "Stephenson", "H\u1ec7", "th\u00edch", "nghi", "d\u1ef1a"]}, {"bbox": [75, 536, 1421, 568], "words": [{"bbox": [75, 543, 194, 563], "text": "Zealandia"}, {"bbox": [202, 543, 254, 568], "text": "(l\u1ee5c:"}, {"bbox": [262, 543, 315, 568], "text": "\u0111\u1ecba)."}, {"bbox": [322, 543, 364, 567], "text": "\u0110\u1ed9i"}, {"bbox": [372, 536, 439, 568], "text": "tuy\u1ec3n"}, {"bbox": [447, 543, 507, 568], "text": "b\u00f3ng"}, {"bbox": [515, 543, 545, 563], "text": "\u0111\u00e1"}, {"bbox": [553, 538, 612, 568], "text": "qu\u1ed1c"}, {"bbox": [620, 543, 656, 568], "text": "gia"}, {"bbox": [664, 543, 825, 563], "text": "Liechtenstein"}, {"bbox": [833, 543, 893, 568], "text": "Mary"}, {"bbox": [901, 543, 933, 563], "text": "x\u1ee9"}, {"bbox": [941, 543, 1012, 563], "text": "Guise"}, {"bbox": [1020, 543, 1082, 568], "text": "Sony"}, {"bbox": [1090, 543, 1203, 567], "text": "Ericsson;"}, {"bbox": [1211, 543, 1289, 568], "text": "Xperia"}, {"bbox": [1297, 543, 1345, 563], "text": "X10"}, {"bbox": [1353, 543, 1421, 563], "text": "Wimb"}], "texts": ["Zealandia", "(l\u1ee5c:", "\u0111\u1ecba).", "\u0110\u1ed9i", "tuy\u1ec3n", "b\u00f3ng", "\u0111\u00e1", "qu\u1ed1c", "gia", "Liechtenstein", "Mary", "x\u1ee9", "Guise", "Sony", "Ericsson;", "Xperia", "X10", "Wimb"]}, {"bbox": [75, 568, 1420, 600], "words": [{"bbox": [75, 575, 122, 595], "text": "T\u00f4n"}, {"bbox": [130, 575, 181, 600], "text": "gi\u00e1o"}, {"bbox": [189, 572, 207, 595], "text": "\u1edf"}, {"bbox": [215, 575, 275, 595], "text": "Lu\u00e2n"}, {"bbox": [282, 575, 333, 595], "text": "\u0110\u00f4n"}, {"bbox": [341, 575, 416, 595], "text": "Marco"}, {"bbox": [424, 580, 476, 599], "text": "van;"}, {"bbox": [484, 575, 569, 595], "text": "Basten"}, {"bbox": [577, 575, 633, 595], "text": "Th\u1eddi"}, {"bbox": [641, 575, 692, 600], "text": "gian"}, {"bbox": [700, 568, 751, 595], "text": "bi\u1ec3u"}, {"bbox": [759, 575, 812, 600], "text": "ph\u00e1t"}, {"bbox": [820, 575, 871, 599], "text": "hi\u1ec7n"}, {"bbox": [879, 575, 922, 595], "text": "c\u00e1c"}, {"bbox": [930, 575, 990, 595], "text": "h\u00e0nh"}, {"bbox": [998, 575, 1042, 595], "text": "tinh"}, {"bbox": [1050, 575, 1079, 595], "text": "v\u00e0"}, {"bbox": [1087, 575, 1116, 599], "text": "v\u1ec7"}, {"bbox": [1124, 575, 1168, 595], "text": "tinh"}, {"bbox": [1176, 575, 1238, 600], "text": "trong"}, {"bbox": [1246, 575, 1281, 599], "text": "H\u1ec7"}, {"bbox": [1289, 575, 1334, 599], "text": "M\u1eb7t"}, {"bbox": [1342, 575, 1392, 595], "text": "Tr\u1eddi"}, {"bbox": [1399, 575, 1419, 595], "text": "H"}], "texts": ["T\u00f4n", "gi\u00e1o", "\u1edf", "Lu\u00e2n", "\u0110\u00f4n", "Marco", "van;", "Basten", "Th\u1eddi", "gian", "bi\u1ec3u", "ph\u00e1t", "hi\u1ec7n", "c\u00e1c", "h\u00e0nh", "tinh", "v\u00e0", "v\u1ec7", "tinh", "trong", "H\u1ec7", "M\u1eb7t", "Tr\u1eddi", "H"]}, {"bbox": [75, 602, 1419, 632], "words": [{"bbox": [75, 607, 131, 627], "text": "S\u00e2nI"}, {"bbox": [139, 607, 183, 632], "text": "bay"}, {"bbox": [191, 607, 241, 627], "text": "Chu"}, {"bbox": [249, 607, 285, 627], "text": "Lai"}, {"bbox": [293, 607, 361, 632], "text": "Sonyl"}, {"bbox": [369, 607, 447, 632], "text": "Xperia"}, {"bbox": [455, 607, 472, 627], "text": "Z"}, {"bbox": [480, 607, 557, 627], "text": "Betula"}, {"bbox": [565, 607, 694, 632], "text": "platyphylla"}, {"bbox": [702, 607, 738, 627], "text": ".ml"}, {"bbox": [746, 607, 774, 627], "text": "R."}, {"bbox": [782, 607, 865, 627], "text": "Harrod"}, {"bbox": [873, 607, 903, 627], "text": "24"}, {"bbox": [911, 607, 979, 632], "text": "th\u00e1ng"}, {"bbox": [987, 607, 1002, 627], "text": "3"}, {"bbox": [1010, 607, 1129, 627], "text": "Techiman"}, {"bbox": [1136, 607, 1195, 627], "text": "Ti\u00eaui"}, {"bbox": [1203, 607, 1251, 632], "text": "(h\u1ecd)"}, {"bbox": [1259, 607, 1313, 627], "text": "Kinh"}, {"bbox": [1321, 602, 1344, 627], "text": "t\u1ebf"}, {"bbox": [1352, 607, 1418, 627], "text": "Mace"}], "texts": ["S\u00e2nI", "bay", "Chu", "Lai", "Sonyl", "Xperia", "Z", "Betula", "platyphylla", ".ml", "R.", "Harrod", "24", "th\u00e1ng", "3", "Techiman", "Ti\u00eaui", "(h\u1ecd)", "Kinh", "t\u1ebf", "Mace"]}, {"bbox": [74, 634, 1423, 664], "words": [{"bbox": [74, 639, 161, 664], "text": "\u0110\u01b0\u1eddng"}, {"bbox": [169, 644, 207, 664], "text": "ray"}, {"bbox": [215, 639, 281, 659], "text": "1713i"}, {"bbox": [289, 639, 394, 659], "text": "Pakistan"}, {"bbox": [402, 639, 468, 659], "text": "Peter"}, {"bbox": [475, 639, 529, 659], "text": "Paul"}, {"bbox": [537, 639, 631, 659], "text": "Rubens"}, {"bbox": [639, 639, 707, 659], "text": "Thi\u00ean"}, {"bbox": [715, 639, 766, 659], "text": "S\u01a1n"}, {"bbox": [774, 639, 834, 664], "text": "(\u0111\u1ecbnh"}, {"bbox": [842, 639, 932, 664], "text": "h\u01b0\u1edbng)"}, {"bbox": [940, 639, 987, 663], "text": "T\u1ea1o"}, {"bbox": [995, 639, 1060, 664], "text": "H\u00e0ng"}, {"bbox": [1068, 634, 1139, 664], "text": "Tr\u1ed1ng"}, {"bbox": [1146, 639, 1275, 664], "text": "(ph\u01b0\u1eddng)?"}, {"bbox": [1283, 639, 1352, 659], "text": "Tam1"}, {"bbox": [1359, 639, 1422, 664], "text": "\u0110i\u1ec7pl"}], "texts": ["\u0110\u01b0\u1eddng", "ray", "1713i", "Pakistan", "Peter", "Paul", "Rubens", "Thi\u00ean", "S\u01a1n", "(\u0111\u1ecbnh", "h\u01b0\u1edbng)", "T\u1ea1o", "H\u00e0ng", "Tr\u1ed1ng", "(ph\u01b0\u1eddng)?", "Tam1", "\u0110i\u1ec7pl"]}, {"bbox": [75, 666, 1425, 696], "words": [{"bbox": [75, 671, 130, 691], "text": "Uwe"}, {"bbox": [138, 671, 271, 691], "text": "H\u00fcnemeier"}, {"bbox": [278, 671, 337, 691], "text": "Lake"}, {"bbox": [345, 671, 442, 691], "text": "Poets\u2014"}, {"bbox": [450, 671, 509, 691], "text": "Nero"}, {"bbox": [517, 666, 583, 693], "text": "Qu\u1ea7n"}, {"bbox": [591, 668, 636, 691], "text": "\u0111\u1ea3o"}, {"bbox": [644, 671, 769, 691], "text": "Sakishima"}, {"bbox": [777, 671, 862, 696], "text": "Thierry"}, {"bbox": [870, 671, 943, 696], "text": "Henry"}, {"bbox": [951, 671, 1078, 691], "text": "Stockholm"}, {"bbox": [1086, 671, 1123, 691], "text": "FC"}, {"bbox": [1131, 671, 1243, 691], "text": "St.Gallen"}, {"bbox": [1251, 671, 1313, 691], "text": "Kh\u00fac"}, {"bbox": [1321, 671, 1365, 691], "text": "c\u00f4n"}, {"bbox": [1373, 666, 1417, 691], "text": "c\u1ea7u"}, {"bbox": [1425, 666, 1425, 666], "text": ""}], "texts": ["Uwe", "H\u00fcnemeier", "Lake", "Poets\u2014", "Nero", "Qu\u1ea7n", "\u0111\u1ea3o", "Sakishima", "Thierry", "Henry", "Stockholm", "FC", "St.Gallen", "Kh\u00fac", "c\u00f4n", "c\u1ea7u", ""]}, {"bbox": [75, 698, 1418, 728], "words": [{"bbox": [75, 700, 123, 723], "text": "Gi\u1ea3i"}, {"bbox": [131, 703, 160, 723], "text": "v\u00f4"}, {"bbox": [168, 703, 218, 727], "text": "\u0111\u1ecbch"}, {"bbox": [226, 703, 286, 728], "text": "b\u00f3ng"}, {"bbox": [294, 703, 324, 723], "text": "\u0111\u00e1"}, {"bbox": [332, 703, 391, 723], "text": "U-17"}, {"bbox": [399, 703, 456, 723], "text": "Nam"}, {"bbox": [464, 703, 500, 728], "text": "M\u1ef9"}, {"bbox": [507, 703, 557, 727], "text": "\u0110\u1ea1i."}, {"bbox": [565, 703, 601, 727], "text": "h\u1ed9i"}, {"bbox": [609, 698, 647, 723], "text": "b\u1ea5t"}, {"bbox": [655, 703, 744, 728], "text": "th\u01b0\u1eddng"}, {"bbox": [752, 703, 813, 723], "text": "FIFA"}, {"bbox": [819, 703, 887, 723], "text": "2016:"}, {"bbox": [895, 703, 1027, 723], "text": "Marasmius"}, {"bbox": [1035, 703, 1133, 723], "text": "oreades"}, {"bbox": [1141, 703, 1213, 723], "text": "Nh\u00f3m"}, {"bbox": [1221, 703, 1281, 728], "text": "ng\u00f4n"}, {"bbox": [1289, 704, 1345, 728], "text": "ng\u1eef;"}, {"bbox": [1353, 703, 1417, 723], "text": "Cush"}], "texts": ["Gi\u1ea3i", "v\u00f4", "\u0111\u1ecbch", "b\u00f3ng", "\u0111\u00e1", "U-17", "Nam", "M\u1ef9", "\u0110\u1ea1i.", "h\u1ed9i", "b\u1ea5t", "th\u01b0\u1eddng", "FIFA", "2016:", "Marasmius", "oreades", "Nh\u00f3m", "ng\u00f4n", "ng\u1eef;", "Cush"]}, {"bbox": [75, 731, 1424, 760], "words": [{"bbox": [75, 732, 126, 757], "text": "Qu\u1ea3"}, {"bbox": [134, 735, 194, 760], "text": "b\u00f3ng"}, {"bbox": [202, 735, 261, 760], "text": "v\u00e0ng"}, {"bbox": [269, 735, 330, 755], "text": "FIFA"}, {"bbox": [336, 735, 388, 755], "text": "M\u00e8o"}, {"bbox": [396, 735, 512, 755], "text": "Munchkin"}, {"bbox": [520, 735, 567, 755], "text": "ISO"}, {"bbox": [575, 735, 658, 755], "text": "10006!"}, {"bbox": [666, 735, 758, 760], "text": "Tr\u01b0\u1eddng"}, {"bbox": [766, 731, 818, 755], "text": "m\u1eabu"}, {"bbox": [826, 735, 893, 760], "text": "gi\u00e1o,."}, {"bbox": [901, 735, 987, 760], "text": "Nghi\u1ec7p"}, {"bbox": [995, 735, 1055, 755], "text": "\u0111o\u00e0n"}, {"bbox": [1062, 735, 1185, 755], "text": "Anousheh"}, {"bbox": [1192, 735, 1278, 759], "text": "Ansari;"}, {"bbox": [1286, 735, 1423, 759], "text": "Willimantic,"}], "texts": ["Qu\u1ea3", "b\u00f3ng", "v\u00e0ng", "FIFA", "M\u00e8o", "Munchkin", "ISO", "10006!", "Tr\u01b0\u1eddng", "m\u1eabu", "gi\u00e1o,.", "Nghi\u1ec7p", "\u0111o\u00e0n", "Anousheh", "Ansari;", "Willimantic,"]}, {"bbox": [75, 760, 1417, 792], "words": [{"bbox": [75, 767, 183, 787], "text": "Rom\u00e2nia"}, {"bbox": [190, 767, 289, 792], "text": "Angevin"}, {"bbox": [297, 767, 390, 792], "text": "Empire;"}, {"bbox": [398, 764, 446, 787], "text": "Gi\u1ea3i"}, {"bbox": [454, 767, 483, 787], "text": "v\u00f4"}, {"bbox": [491, 767, 541, 791], "text": "\u0111\u1ecbch"}, {"bbox": [549, 767, 609, 792], "text": "b\u00f3ng"}, {"bbox": [617, 767, 647, 787], "text": "\u0111\u00e1"}, {"bbox": [655, 768, 688, 787], "text": "n\u1eef"}, {"bbox": [696, 767, 755, 787], "text": "U-20"}, {"bbox": [763, 762, 801, 787], "text": "th\u1ebf"}, {"bbox": [809, 767, 854, 792], "text": "gi\u1edbi"}, {"bbox": [862, 767, 922, 787], "text": "2016"}, {"bbox": [930, 760, 984, 787], "text": "Bi\u1ec3n"}, {"bbox": [992, 767, 1089, 787], "text": "Lazarev"}, {"bbox": [1097, 767, 1142, 787], "text": "S\u00e0ii"}, {"bbox": [1150, 767, 1209, 791], "text": "G\u00f2n,"}, {"bbox": [1217, 767, 1262, 787], "text": "anh"}, {"bbox": [1270, 767, 1314, 792], "text": "y\u00eau"}, {"bbox": [1322, 772, 1359, 787], "text": "em"}, {"bbox": [1366, 764, 1417, 787], "text": "\u0110\u1ea3n"}], "texts": ["Rom\u00e2nia", "Angevin", "Empire;", "Gi\u1ea3i", "v\u00f4", "\u0111\u1ecbch", "b\u00f3ng", "\u0111\u00e1", "n\u1eef", "U-20", "th\u1ebf", "gi\u1edbi", "2016", "Bi\u1ec3n", "Lazarev", "S\u00e0ii", "G\u00f2n,", "anh", "y\u00eau", "em", "\u0110\u1ea3n"]}, {"bbox": [75, 794, 1423, 824], "words": [{"bbox": [75, 799, 122, 819], "text": "T\u00e0u"}, {"bbox": [130, 799, 174, 819], "text": "khu"}, {"bbox": [182, 799, 228, 823], "text": "tr\u1ee5c"}, {"bbox": [236, 799, 281, 824], "text": "l\u1edbpl"}, {"bbox": [289, 799, 416, 823], "text": "Takanami,"}, {"bbox": [423, 799, 525, 824], "text": "Baroque"}, {"bbox": [533, 804, 578, 824], "text": "pop"}, {"bbox": [586, 794, 654, 824], "text": "Ti\u1ebfng"}, {"bbox": [662, 794, 720, 819], "text": "Mi\u1ebfn"}, {"bbox": [727, 799, 792, 823], "text": "\u0110i\u1ec7n,"}, {"bbox": [800, 796, 850, 819], "text": "Ch\u1ee7"}, {"bbox": [858, 799, 934, 824], "text": "ngh\u0129a;"}, {"bbox": [942, 799, 1001, 824], "text": "c\u1ed9ng"}, {"bbox": [1009, 796, 1062, 819], "text": "s\u1ea3n-"}, {"bbox": [1070, 799, 1185, 824], "text": "Budapest"}, {"bbox": [1193, 799, 1323, 824], "text": "Sparsbach"}, {"bbox": [1331, 799, 1372, 819], "text": "Ph\u00ed"}, {"bbox": [1380, 799, 1422, 824], "text": "(n\u01b0"}], "texts": ["T\u00e0u", "khu", "tr\u1ee5c", "l\u1edbpl", "Takanami,", "Baroque", "pop", "Ti\u1ebfng", "Mi\u1ebfn", "\u0110i\u1ec7n,", "Ch\u1ee7", "ngh\u0129a;", "c\u1ed9ng", "s\u1ea3n-", "Budapest", "Sparsbach", "Ph\u00ed", "(n\u01b0"]}, {"bbox": [75, 824, 1422, 856], "words": [{"bbox": [75, 831, 138, 851], "text": "Sao1"}, {"bbox": [146, 831, 197, 855], "text": "M\u1ed9c"}, {"bbox": [205, 831, 237, 851], "text": "Dil"}, {"bbox": [245, 828, 281, 851], "text": "ch\u1ec9"}, {"bbox": [288, 831, 335, 851], "text": "th\u1eddi"}, {"bbox": [343, 826, 373, 851], "text": "\u0111\u1ed3"}, {"bbox": [381, 831, 411, 851], "text": "\u0111\u00e1"}, {"bbox": [419, 831, 465, 851], "text": "m\u1edbi"}, {"bbox": [473, 828, 491, 851], "text": "\u1edf"}, {"bbox": [499, 831, 587, 856], "text": "Orkney"}, {"bbox": [595, 831, 650, 851], "text": "Post"}, {"bbox": [658, 831, 724, 855], "text": "Falls,"}, {"bbox": [732, 831, 815, 851], "text": "Idaho1"}, {"bbox": [823, 831, 864, 851], "text": "Kh\u00ed"}, {"bbox": [872, 831, 917, 855], "text": "h\u1eadu"}, {"bbox": [925, 824, 976, 851], "text": "bi\u1ec3n"}, {"bbox": [984, 831, 1033, 851], "text": "C\u00e1c"}, {"bbox": [1041, 836, 1070, 855], "text": "v\u1ee5"}, {"bbox": [1078, 831, 1128, 855], "text": "ki\u1ec7n"}, {"bbox": [1136, 831, 1187, 855], "text": "\u0111i\u1ec7n"}, {"bbox": [1195, 831, 1254, 855], "text": "tho\u1ea1i"}, {"bbox": [1262, 828, 1315, 851], "text": "C\u1eeda"}, {"bbox": [1323, 824, 1382, 851], "text": "kh\u1ea9u"}, {"bbox": [1390, 831, 1422, 851], "text": "T\u00e2"}], "texts": ["Sao1", "M\u1ed9c", "Dil", "ch\u1ec9", "th\u1eddi", "\u0111\u1ed3", "\u0111\u00e1", "m\u1edbi", "\u1edf", "Orkney", "Post", "Falls,", "Idaho1", "Kh\u00ed", "h\u1eadu", "bi\u1ec3n", "C\u00e1c", "v\u1ee5", "ki\u1ec7n", "\u0111i\u1ec7n", "tho\u1ea1i", "C\u1eeda", "kh\u1ea9u", "T\u00e2"]}, {"bbox": [75, 858, 1418, 888], "words": [{"bbox": [75, 863, 198, 888], "text": "Singapore"}, {"bbox": [206, 863, 262, 887], "text": "Tr\u1eadn"}, {"bbox": [269, 863, 325, 883], "text": "B\u00ecnh"}, {"bbox": [333, 863, 383, 887], "text": "Gi\u00e3;"}, {"bbox": [391, 863, 464, 883], "text": "Ch\u00ednh"}, {"bbox": [472, 860, 517, 888], "text": "ph\u1ee7"}, {"bbox": [525, 863, 572, 887], "text": "Vi\u1ec7t"}, {"bbox": [580, 863, 637, 883], "text": "Nam"}, {"bbox": [645, 863, 789, 883], "text": "1971-1975?"}, {"bbox": [797, 863, 853, 888], "text": "Hi\u1ec7p"}, {"bbox": [861, 863, 903, 887], "text": "h\u1ed9il"}, {"bbox": [911, 863, 971, 888], "text": "b\u00f3ng"}, {"bbox": [979, 863, 1009, 883], "text": "\u0111\u00e1"}, {"bbox": [1017, 858, 1083, 885], "text": "Qu\u1ea7n"}, {"bbox": [1091, 860, 1136, 883], "text": "\u0111\u1ea3o"}, {"bbox": [1144, 863, 1215, 883], "text": "Faroe"}, {"bbox": [1223, 863, 1339, 887], "text": "Rom\u00e2nia,"}, {"bbox": [1346, 863, 1397, 887], "text": "\u0110\u1ea1o"}, {"bbox": [1405, 863, 1417, 883], "text": "li"}], "texts": ["Singapore", "Tr\u1eadn", "B\u00ecnh", "Gi\u00e3;", "Ch\u00ednh", "ph\u1ee7", "Vi\u1ec7t", "Nam", "1971-1975?", "Hi\u1ec7p", "h\u1ed9il", "b\u00f3ng", "\u0111\u00e1", "Qu\u1ea7n", "\u0111\u1ea3o", "Faroe", "Rom\u00e2nia,", "\u0110\u1ea1o", "li"]}, {"bbox": [75, 888, 1417, 920], "words": [{"bbox": [75, 895, 165, 915], "text": "Rock\u2014"}, {"bbox": [173, 895, 287, 915], "text": "Cestoball"}, {"bbox": [295, 888, 348, 915], "text": "Ti\u1ec3u"}, {"bbox": [355, 895, 415, 920], "text": "bang"}, {"bbox": [423, 895, 462, 915], "text": "X\u00f4l"}, {"bbox": [470, 890, 517, 915], "text": "Vi\u1ebft"}, {"bbox": [525, 895, 652, 920], "text": "Wikiquote;"}, {"bbox": [660, 895, 709, 915], "text": "C\u00e1c"}, {"bbox": [717, 890, 777, 920], "text": "\u0111\u1ed3ng"}, {"bbox": [785, 890, 829, 915], "text": "ti\u1ec1n"}, {"bbox": [837, 890, 887, 920], "text": "gi\u1ea5y"}, {"bbox": [895, 895, 970, 920], "text": "pound"}, {"bbox": [978, 895, 1074, 920], "text": "sterling;"}, {"bbox": [1082, 895, 1176, 920], "text": "Nguy\u00ean"}, {"bbox": [1184, 895, 1221, 915], "text": "\u00e2m"}, {"bbox": [1229, 895, 1276, 915], "text": "tr\u00f2n"}, {"bbox": [1284, 895, 1351, 915], "text": "tr\u01b0\u1edbc"}, {"bbox": [1359, 895, 1416, 915], "text": "Ham"}], "texts": ["Rock\u2014", "Cestoball", "Ti\u1ec3u", "bang", "X\u00f4l", "Vi\u1ebft", "Wikiquote;", "C\u00e1c", "\u0111\u1ed3ng", "ti\u1ec1n", "gi\u1ea5y", "pound", "sterling;", "Nguy\u00ean", "\u00e2m", "tr\u00f2n", "tr\u01b0\u1edbc", "Ham"]}, {"bbox": [75, 922, 1410, 952], "words": [{"bbox": [75, 927, 126, 952], "text": "M\u00e1y"}, {"bbox": [134, 922, 185, 947], "text": "bi\u1ebfn"}, {"bbox": [193, 927, 253, 952], "text": "n\u0103ng"}, {"bbox": [261, 927, 383, 952], "text": "Dentsply1"}, {"bbox": [391, 927, 469, 947], "text": "Sirona"}, {"bbox": [477, 927, 555, 947], "text": "Michel"}, {"bbox": [563, 927, 642, 947], "text": "Piccoli"}, {"bbox": [650, 927, 715, 947], "text": "H\u00e0nh"}, {"bbox": [723, 927, 790, 947], "text": "ch\u00ednh"}, {"bbox": [798, 927, 851, 947], "text": "Th\u00e1i"}, {"bbox": [859, 927, 912, 947], "text": "Lan!"}, {"bbox": [920, 927, 956, 947], "text": "SV"}, {"bbox": [964, 927, 1053, 947], "text": "Werder"}, {"bbox": [1060, 927, 1154, 947], "text": "Bremen"}, {"bbox": [1161, 927, 1212, 947], "text": "\u0110an"}, {"bbox": [1220, 927, 1286, 951], "text": "M\u1ea1ch"}, {"bbox": [1294, 927, 1402, 952], "text": "Jorkyball"}, {"bbox": [1410, 922, 1410, 922], "text": ""}], "texts": ["M\u00e1y", "bi\u1ebfn", "n\u0103ng", "Dentsply1", "Sirona", "Michel", "Piccoli", "H\u00e0nh", "ch\u00ednh", "Th\u00e1i", "Lan!", "SV", "Werder", "Bremen", "\u0110an", "M\u1ea1ch", "Jorkyball", ""]}, {"bbox": [75, 959, 1425, 984], "words": [{"bbox": [75, 959, 110, 979], "text": "Na"}, {"bbox": [118, 959, 160, 984], "text": "UyI"}, {"bbox": [168, 959, 274, 979], "text": "Northern"}, {"bbox": [282, 959, 377, 979], "text": "Premier"}, {"bbox": [384, 959, 482, 984], "text": "League:"}, {"bbox": [490, 959, 595, 979], "text": "1976\u201377"}, {"bbox": [603, 959, 669, 979], "text": "Peter"}, {"bbox": [676, 959, 797, 979], "text": "Canisius!."}, {"bbox": [805, 959, 865, 979], "text": "2001"}, {"bbox": [873, 959, 952, 979], "text": "C\u00e1ch1"}, {"bbox": [960, 964, 1027, 984], "text": "m\u1ea1ng"}, {"bbox": [1035, 959, 1098, 984], "text": "Ph\u00e1p"}, {"bbox": [1106, 959, 1174, 979], "text": "Taisir"}, {"bbox": [1179, 959, 1298, 979], "text": "Al-Jassim"}, {"bbox": [1306, 959, 1383, 979], "text": "Pelota"}, {"bbox": [1391, 959, 1424, 979], "text": "Ba"}], "texts": ["Na", "UyI", "Northern", "Premier", "League:", "1976\u201377", "Peter", "Canisius!.", "2001", "C\u00e1ch1", "m\u1ea1ng", "Ph\u00e1p", "Taisir", "Al-Jassim", "Pelota", "Ba"]}, {"bbox": [75, 986, 1423, 1016], "words": [{"bbox": [75, 991, 131, 1016], "text": "Hi\u1ec7p"}, {"bbox": [139, 991, 189, 1011], "text": "\u01b0\u1edbc"}, {"bbox": [197, 991, 297, 1016], "text": "Rapallo,"}, {"bbox": [305, 991, 365, 1011], "text": "1920"}, {"bbox": [373, 991, 508, 1016], "text": "TouchLight"}, {"bbox": [515, 991, 565, 1015], "text": "H\u1eadu"}, {"bbox": [573, 986, 617, 1011], "text": "c\u1ea7n"}, {"bbox": [625, 991, 687, 1016], "text": "trong"}, {"bbox": [695, 986, 766, 1011], "text": "Chi\u1ebfn"}, {"bbox": [774, 991, 824, 1015], "text": "d\u1ecbch"}, {"bbox": [831, 991, 888, 1015], "text": "\u0110i\u1ec7n"}, {"bbox": [896, 991, 950, 1011], "text": "Bi\u00ean"}, {"bbox": [958, 988, 1021, 1011], "text": "Ph\u1ee7?"}, {"bbox": [1028, 991, 1079, 1011], "text": "\u0110\u00e0o"}, {"bbox": [1087, 988, 1150, 1011], "text": "Kh\u1ea3n"}, {"bbox": [1158, 986, 1205, 1011], "text": "B\u1eafc"}, {"bbox": [1213, 991, 1284, 1016], "text": "Trung"}, {"bbox": [1292, 986, 1357, 1013], "text": "Qu\u1ed1c"}, {"bbox": [1365, 991, 1422, 1011], "text": "Cam"}], "texts": ["Hi\u1ec7p", "\u01b0\u1edbc", "Rapallo,", "1920", "TouchLight", "H\u1eadu", "c\u1ea7n", "trong", "Chi\u1ebfn", "d\u1ecbch", "\u0110i\u1ec7n", "Bi\u00ean", "Ph\u1ee7?", "\u0110\u00e0o", "Kh\u1ea3n", "B\u1eafc", "Trung", "Qu\u1ed1c", "Cam"]}, {"bbox": [75, 1018, 1420, 1048], "words": [{"bbox": [75, 1023, 133, 1043], "text": "PGA"}, {"bbox": [139, 1023, 196, 1043], "text": "Tour"}, {"bbox": [203, 1023, 348, 1048], "text": "Champions;"}, {"bbox": [356, 1023, 386, 1043], "text": "15"}, {"bbox": [394, 1023, 462, 1048], "text": "th\u00e1ng"}, {"bbox": [470, 1023, 508, 1047], "text": "12,"}, {"bbox": [516, 1020, 572, 1043], "text": "Ch\u1ee7i"}, {"bbox": [580, 1023, 656, 1048], "text": "ngh\u0129a;"}, {"bbox": [664, 1020, 738, 1048], "text": "kh\u1ee7ng"}, {"bbox": [746, 1018, 776, 1043], "text": "b\u1ed1"}, {"bbox": [784, 1023, 870, 1043], "text": "William"}, {"bbox": [878, 1023, 987, 1043], "text": "Paterson"}, {"bbox": [995, 1020, 1048, 1048], "text": "(ch\u1ee7"}, {"bbox": [1056, 1023, 1116, 1048], "text": "ng\u00e2n"}, {"bbox": [1124, 1023, 1199, 1048], "text": "h\u00e0ng)i"}, {"bbox": [1207, 1023, 1272, 1048], "text": "C\u00f4ng"}, {"bbox": [1280, 1023, 1338, 1043], "text": "t\u01b0\u1edbc"}, {"bbox": [1346, 1023, 1378, 1043], "text": "x\u1ee9"}, {"bbox": [1386, 1023, 1419, 1043], "text": "Su"}], "texts": ["PGA", "Tour", "Champions;", "15", "th\u00e1ng", "12,", "Ch\u1ee7i", "ngh\u0129a;", "kh\u1ee7ng", "b\u1ed1", "William", "Paterson", "(ch\u1ee7", "ng\u00e2n", "h\u00e0ng)i", "C\u00f4ng", "t\u01b0\u1edbc", "x\u1ee9", "Su"]}, {"bbox": [75, 1050, 1421, 1080], "words": [{"bbox": [75, 1055, 129, 1075], "text": "Paul"}, {"bbox": [137, 1055, 234, 1075], "text": "Doumer"}, {"bbox": [240, 1055, 393, 1080], "text": "Afghanistan;"}, {"bbox": [401, 1055, 466, 1075], "text": "H\u00e0nh"}, {"bbox": [474, 1055, 534, 1080], "text": "\u0111\u1ed9ng"}, {"bbox": [541, 1055, 598, 1075], "text": "\u0110inh"}, {"bbox": [606, 1055, 652, 1079], "text": "Th\u1ecbI"}, {"bbox": [660, 1055, 722, 1079], "text": "B\u1ea1ch"}, {"bbox": [730, 1055, 800, 1075], "text": "Mai\u2014"}, {"bbox": [808, 1055, 873, 1075], "text": "Danh"}, {"bbox": [881, 1055, 939, 1075], "text": "s\u00e1ch"}, {"bbox": [947, 1055, 993, 1075], "text": "t\u00ednh"}, {"bbox": [1001, 1055, 1071, 1080], "text": "trung."}, {"bbox": [1079, 1055, 1115, 1080], "text": "l\u1eadp"}, {"bbox": [1123, 1055, 1158, 1075], "text": "v\u00e0l"}, {"bbox": [1166, 1055, 1212, 1075], "text": "t\u00ednh"}, {"bbox": [1220, 1055, 1267, 1075], "text": "v\u1eeba"}, {"bbox": [1275, 1050, 1319, 1075], "text": "x\u1ea5u"}, {"bbox": [1327, 1055, 1374, 1075], "text": "v\u1eeba"}, {"bbox": [1382, 1050, 1421, 1075], "text": "t\u1ed1t!"}], "texts": ["Paul", "Doumer", "Afghanistan;", "H\u00e0nh", "\u0111\u1ed9ng", "\u0110inh", "Th\u1ecbI", "B\u1ea1ch", "Mai\u2014", "Danh", "s\u00e1ch", "t\u00ednh", "trung.", "l\u1eadp", "v\u00e0l", "t\u00ednh", "v\u1eeba", "x\u1ea5u", "v\u1eeba", "t\u1ed1t!"]}, {"bbox": [75, 1080, 1422, 1112], "words": [{"bbox": [75, 1087, 125, 1111], "text": "H\u1ec71"}, {"bbox": [133, 1087, 193, 1112], "text": "ng\u00f4n"}, {"bbox": [201, 1088, 249, 1112], "text": "ng\u1eef"}, {"bbox": [256, 1087, 298, 1111], "text": "\u0110\u1ed9i"}, {"bbox": [306, 1080, 373, 1112], "text": "tuy\u1ec3n"}, {"bbox": [381, 1087, 441, 1112], "text": "b\u00f3ng"}, {"bbox": [449, 1087, 479, 1107], "text": "\u0111\u00e1"}, {"bbox": [487, 1082, 546, 1112], "text": "qu\u1ed1c"}, {"bbox": [554, 1087, 590, 1112], "text": "gia"}, {"bbox": [598, 1087, 665, 1107], "text": "Tahiti"}, {"bbox": [671, 1087, 713, 1111], "text": "\u0110\u1ea1i"}, {"bbox": [721, 1087, 765, 1111], "text": "h\u1ecdc"}, {"bbox": [773, 1087, 860, 1107], "text": "Huston"}, {"bbox": [868, 1087, 903, 1111], "text": "t\u1ea1il"}, {"bbox": [911, 1087, 977, 1107], "text": "Clear"}, {"bbox": [984, 1087, 1051, 1111], "text": "Lake;"}, {"bbox": [1059, 1087, 1116, 1107], "text": "Nam"}, {"bbox": [1123, 1081, 1157, 1107], "text": "\u00c2u"}, {"bbox": [1165, 1087, 1230, 1107], "text": "Henri"}, {"bbox": [1238, 1087, 1375, 1107], "text": "Frankfort\u2014"}, {"bbox": [1383, 1087, 1421, 1107], "text": "H\u01b0"}], "texts": ["H\u1ec71", "ng\u00f4n", "ng\u1eef", "\u0110\u1ed9i", "tuy\u1ec3n", "b\u00f3ng", "\u0111\u00e1", "qu\u1ed1c", "gia", "Tahiti", "\u0110\u1ea1i", "h\u1ecdc", "Huston", "t\u1ea1il", "Clear", "Lake;", "Nam", "\u00c2u", "Henri", "Frankfort\u2014", "H\u01b0"]}, {"bbox": [75, 1114, 1420, 1144], "words": [{"bbox": [75, 1119, 146, 1144], "text": "Trung"}, {"bbox": [153, 1119, 189, 1143], "text": "\u0111\u1ed9i"}, {"bbox": [197, 1119, 326, 1139], "text": "Parliament"}, {"bbox": [334, 1119, 358, 1139], "text": "of"}, {"bbox": [365, 1119, 471, 1139], "text": "Scotland"}, {"bbox": [479, 1119, 529, 1139], "text": "Con"}, {"bbox": [537, 1119, 588, 1139], "text": "nu\u00f4i"}, {"bbox": [596, 1114, 662, 1141], "text": "Qu\u1ea7n"}, {"bbox": [670, 1116, 715, 1139], "text": "\u0111\u1ea3o"}, {"bbox": [723, 1119, 815, 1144], "text": "Tr\u01b0\u1eddng"}, {"bbox": [823, 1119, 864, 1143], "text": "Sa;"}, {"bbox": [872, 1119, 937, 1144], "text": "C\u00f4ng"}, {"bbox": [945, 1119, 1039, 1144], "text": "Nguy\u00ean"}, {"bbox": [1047, 1119, 1131, 1144], "text": "V\u01b0\u01a1ng"}, {"bbox": [1139, 1114, 1192, 1139], "text": "tri\u1ec1u"}, {"bbox": [1200, 1119, 1291, 1139], "text": "Safavid"}, {"bbox": [1299, 1119, 1353, 1139], "text": "NTT"}, {"bbox": [1361, 1119, 1419, 1139], "text": "Data"}], "texts": ["Trung", "\u0111\u1ed9i", "Parliament", "of", "Scotland", "Con", "nu\u00f4i", "Qu\u1ea7n", "\u0111\u1ea3o", "Tr\u01b0\u1eddng", "Sa;", "C\u00f4ng", "Nguy\u00ean", "V\u01b0\u01a1ng", "tri\u1ec1u", "Safavid", "NTT", "Data"]}, {"bbox": [75, 1148, 1409, 1176], "words": [{"bbox": [75, 1148, 125, 1171], "text": "Ch\u1ee7"}, {"bbox": [133, 1151, 201, 1176], "text": "ngh\u0129a"}, {"bbox": [209, 1151, 264, 1175], "text": "th\u1ef1c"}, {"bbox": [272, 1151, 332, 1176], "text": "d\u1ee5ng"}, {"bbox": [340, 1151, 400, 1171], "text": "1989"}, {"bbox": [408, 1151, 490, 1176], "text": "(album"}, {"bbox": [498, 1148, 542, 1171], "text": "c\u1ee7a"}, {"bbox": [550, 1151, 627, 1176], "text": "Taylor"}, {"bbox": [633, 1151, 702, 1176], "text": "Swift)"}, {"bbox": [710, 1151, 768, 1171], "text": "H\u00ecnh"}, {"bbox": [776, 1151, 844, 1176], "text": "thang"}, {"bbox": [852, 1151, 896, 1171], "text": "c\u00e2n"}, {"bbox": [904, 1151, 959, 1175], "text": "Tab,"}, {"bbox": [967, 1151, 1048, 1171], "text": "Titanic"}, {"bbox": [1056, 1151, 1174, 1175], "text": "Memorial,"}, {"bbox": [1182, 1151, 1266, 1171], "text": "Belfast"}, {"bbox": [1274, 1151, 1400, 1171], "text": "Mardonius"}, {"bbox": [1408, 1146, 1408, 1146], "text": ""}], "texts": ["Ch\u1ee7", "ngh\u0129a", "th\u1ef1c", "d\u1ee5ng", "1989", "(album", "c\u1ee7a", "Taylor", "Swift)", "H\u00ecnh", "thang", "c\u00e2n", "Tab,", "Titanic", "Memorial,", "Belfast", "Mardonius", ""]}, {"bbox": [75, 1177, 1425, 1208], "words": [{"bbox": [75, 1183, 140, 1203], "text": "Gi\u00e1o."}, {"bbox": [148, 1183, 223, 1208], "text": "ho\u00e0ng"}, {"bbox": [231, 1183, 336, 1208], "text": "Gr\u00eag\u00f4ri\u00f4"}, {"bbox": [344, 1183, 386, 1203], "text": "XIII"}, {"bbox": [394, 1177, 459, 1208], "text": "\u0160port"}, {"bbox": [467, 1183, 502, 1203], "text": "TV"}, {"bbox": [510, 1183, 632, 1208], "text": "(Slovenia)"}, {"bbox": [639, 1183, 747, 1203], "text": "Amazon!"}, {"bbox": [755, 1183, 823, 1203], "text": "Basin"}, {"bbox": [831, 1183, 885, 1203], "text": "Kinh"}, {"bbox": [893, 1178, 924, 1203], "text": "t\u1ebfI"}, {"bbox": [932, 1183, 1028, 1208], "text": "Georgia"}, {"bbox": [1036, 1183, 1134, 1203], "text": "Tharu\u2014"}, {"bbox": [1141, 1183, 1198, 1207], "text": "Anh;"}, {"bbox": [1206, 1183, 1254, 1207], "text": "V\u1eadn"}, {"bbox": [1262, 1180, 1291, 1203], "text": "t\u1ea3i"}, {"bbox": [1299, 1183, 1399, 1203], "text": "Rwanda"}, {"bbox": [1407, 1183, 1425, 1203], "text": "V"}], "texts": ["Gi\u00e1o.", "ho\u00e0ng", "Gr\u00eag\u00f4ri\u00f4", "XIII", "\u0160port", "TV", "(Slovenia)", "Amazon!", "Basin", "Kinh", "t\u1ebfI", "Georgia", "Tharu\u2014", "Anh;", "V\u1eadn", "t\u1ea3i", "Rwanda", "V"]}, {"bbox": [75, 1208, 1421, 1240], "words": [{"bbox": [75, 1215, 105, 1235], "text": "26"}, {"bbox": [113, 1215, 181, 1240], "text": "th\u00e1ng"}, {"bbox": [189, 1215, 204, 1235], "text": "1"}, {"bbox": [212, 1215, 306, 1235], "text": "Charles"}, {"bbox": [314, 1215, 322, 1235], "text": "I"}, {"bbox": [330, 1212, 374, 1235], "text": "c\u1ee7a"}, {"bbox": [381, 1215, 430, 1235], "text": "Anh"}, {"bbox": [438, 1215, 488, 1235], "text": "Nh\u00e0"}, {"bbox": [496, 1215, 546, 1235], "text": "H\u00e1n"}, {"bbox": [554, 1210, 587, 1235], "text": "S\u1ed1"}, {"bbox": [595, 1215, 625, 1235], "text": "La"}, {"bbox": [633, 1215, 678, 1235], "text": "M\u00e3!"}, {"bbox": [686, 1215, 757, 1240], "text": "Trung"}, {"bbox": [764, 1208, 799, 1235], "text": "C\u1ed5"}, {"bbox": [807, 1215, 822, 1235], "text": "9"}, {"bbox": [830, 1215, 898, 1240], "text": "th\u00e1ng"}, {"bbox": [906, 1215, 944, 1239], "text": "10;"}, {"bbox": [951, 1215, 993, 1239], "text": "\u0110\u1ea1i"}, {"bbox": [1001, 1215, 1037, 1239], "text": "h\u1ed9i"}, {"bbox": [1045, 1215, 1106, 1235], "text": "FIFA"}, {"bbox": [1113, 1210, 1149, 1235], "text": "l\u1ea7n"}, {"bbox": [1157, 1215, 1198, 1235], "text": "th\u1ee9"}, {"bbox": [1206, 1215, 1245, 1235], "text": "65-"}, {"bbox": [1253, 1215, 1321, 1239], "text": "1748;"}, {"bbox": [1329, 1215, 1420, 1235], "text": "Shamel"}], "texts": ["26", "th\u00e1ng", "1", "Charles", "I", "c\u1ee7a", "Anh", "Nh\u00e0", "H\u00e1n", "S\u1ed1", "La", "M\u00e3!", "Trung", "C\u1ed5", "9", "th\u00e1ng", "10;", "\u0110\u1ea1i", "h\u1ed9i", "FIFA", "l\u1ea7n", "th\u1ee9", "65-", "1748;", "Shamel"]}, {"bbox": [75, 1242, 1418, 1272], "words": [{"bbox": [75, 1247, 189, 1267], "text": "Protoavis"}, {"bbox": [197, 1247, 343, 1272], "text": "CenturyLink"}, {"bbox": [351, 1247, 412, 1267], "text": "Bukit"}, {"bbox": [420, 1247, 495, 1267], "text": "Timah"}, {"bbox": [502, 1247, 547, 1267], "text": "L\u00e0o"}, {"bbox": [555, 1247, 596, 1267], "text": "Cai"}, {"bbox": [604, 1247, 681, 1272], "text": "(th\u00e0nh"}, {"bbox": [689, 1242, 743, 1272], "text": "ph\u1ed1)"}, {"bbox": [751, 1247, 877, 1267], "text": "Nemuranu"}, {"bbox": [885, 1247, 957, 1267], "text": "Machi"}, {"bbox": [965, 1252, 995, 1267], "text": "no"}, {"bbox": [1003, 1247, 1133, 1267], "text": "Cinderella:"}, {"bbox": [1141, 1247, 1220, 1267], "text": "Hirose"}, {"bbox": [1228, 1247, 1333, 1272], "text": "Ryouichi"}, {"bbox": [1341, 1259, 1350, 1267], "text": "-"}, {"bbox": [1358, 1247, 1417, 1267], "text": "Mem"}], "texts": ["Protoavis", "CenturyLink", "Bukit", "Timah", "L\u00e0o", "Cai", "(th\u00e0nh", "ph\u1ed1)", "Nemuranu", "Machi", "no", "Cinderella:", "Hirose", "Ryouichi", "-", "Mem"]}, {"bbox": [75, 1279, 101, 1299], "words": [{"bbox": [75, 1279, 101, 1299], "text": "\u041b."}], "texts": ["\u041b"]}], "bbox": [75, 443, 1425, 1306]}, {"component": "paragraph", "lines": [{"bbox": [75, 1309, 1419, 1341], "words": [{"bbox": [75, 1315, 146, 1339], "text": "Sano,"}, {"bbox": [154, 1315, 250, 1340], "text": "Tochigi;"}, {"bbox": [257, 1315, 349, 1339], "text": "Suffolk;"}, {"bbox": [357, 1315, 462, 1341], "text": "Fran\u00e7ois"}, {"bbox": [470, 1315, 478, 1335], "text": "I"}, {"bbox": [486, 1312, 530, 1335], "text": "c\u1ee7a"}, {"bbox": [538, 1315, 609, 1340], "text": "Ph\u00e1p;"}, {"bbox": [617, 1309, 651, 1335], "text": "\u00dac"}, {"bbox": [659, 1315, 717, 1339], "text": "Golf,"}, {"bbox": [725, 1315, 812, 1335], "text": "Marcell"}, {"bbox": [820, 1315, 908, 1335], "text": "Jansen"}, {"bbox": [916, 1315, 1053, 1340], "text": "Buckcherry"}, {"bbox": [1061, 1315, 1076, 1335], "text": "3"}, {"bbox": [1084, 1315, 1152, 1340], "text": "th\u00e1ng"}, {"bbox": [1160, 1315, 1175, 1335], "text": "7"}, {"bbox": [1183, 1315, 1287, 1340], "text": "Georges"}, {"bbox": [1295, 1315, 1418, 1335], "text": "Condomin"}], "texts": ["Sano,", "Tochigi;", "Suffolk;", "Fran\u00e7ois", "I", "c\u1ee7a", "Ph\u00e1p;", "\u00dac", "Golf,", "Marcell", "Jansen", "Buckcherry", "3", "th\u00e1ng", "7", "Georges", "Condomin"]}, {"bbox": [74, 1343, 1424, 1373], "words": [{"bbox": [74, 1343, 140, 1373], "text": "\u0110\u1ed3ng"}, {"bbox": [148, 1348, 219, 1368], "text": "H\u1edbi\u2014"}, {"bbox": [227, 1348, 257, 1368], "text": "11"}, {"bbox": [264, 1348, 332, 1373], "text": "th\u00e1ng"}, {"bbox": [340, 1348, 370, 1368], "text": "10"}, {"bbox": [378, 1348, 459, 1373], "text": "Khojali"}, {"bbox": [467, 1348, 546, 1373], "text": "Rayon"}, {"bbox": [554, 1348, 626, 1368], "text": "ISBN!"}, {"bbox": [634, 1348, 682, 1368], "text": "Karl"}, {"bbox": [690, 1348, 750, 1368], "text": "Marx"}, {"bbox": [758, 1348, 805, 1368], "text": "Thu"}, {"bbox": [813, 1348, 876, 1368], "text": "Serie"}, {"bbox": [883, 1348, 903, 1368], "text": "A"}, {"bbox": [910, 1348, 1017, 1372], "text": "1977-78;"}, {"bbox": [1025, 1348, 1119, 1373], "text": "Jiangsu"}, {"bbox": [1127, 1348, 1211, 1373], "text": "Suning"}, {"bbox": [1219, 1348, 1280, 1372], "text": "F.C.;"}, {"bbox": [1288, 1348, 1350, 1372], "text": "Tr\u1ecbnh"}, {"bbox": [1358, 1348, 1423, 1373], "text": "C\u00f4ng"}], "texts": ["\u0110\u1ed3ng", "H\u1edbi\u2014", "11", "th\u00e1ng", "10", "Khojali", "Rayon", "ISBN!", "Karl", "Marx", "Thu", "Serie", "A", "1977-78;", "Jiangsu", "Suning", "F.C.;", "Tr\u1ecbnh", "C\u00f4ng"]}, {"bbox": [75, 1377, 1421, 1407], "words": [{"bbox": [75, 1382, 187, 1406], "text": "Bishkek;!"}, {"bbox": [195, 1377, 263, 1407], "text": "Ti\u1ebfng"}, {"bbox": [270, 1382, 341, 1407], "text": "Trung"}, {"bbox": [349, 1382, 393, 1402], "text": "v\u0103n"}, {"bbox": [401, 1377, 444, 1402], "text": "vi\u1ebft"}, {"bbox": [452, 1382, 571, 1402], "text": "Zealandia"}, {"bbox": [579, 1382, 623, 1407], "text": "(l\u1ee5c"}, {"bbox": [631, 1382, 691, 1407], "text": "\u0111\u1ecba)?"}, {"bbox": [698, 1377, 749, 1402], "text": "\u0110\u1ea7u"}, {"bbox": [757, 1387, 789, 1402], "text": "c\u01a1"}, {"bbox": [797, 1382, 921, 1402], "text": "Wikimedia"}, {"bbox": [929, 1382, 1068, 1406], "text": "Commons;I"}, {"bbox": [1076, 1378, 1176, 1407], "text": "Nguy\u1ec5nl"}, {"bbox": [1184, 1382, 1247, 1402], "text": "Xu\u00e2n"}, {"bbox": [1255, 1379, 1353, 1407], "text": "Th\u01b0\u1edfng"}, {"bbox": [1361, 1382, 1420, 1402], "text": "Li\u00eanI"}], "texts": ["Bishkek;!", "Ti\u1ebfng", "Trung", "v\u0103n", "vi\u1ebft", "Zealandia", "(l\u1ee5c", "\u0111\u1ecba)?", "\u0110\u1ea7u", "c\u01a1", "Wikimedia", "Commons;I", "Nguy\u1ec5nl", "Xu\u00e2n", "Th\u01b0\u1edfng", "Li\u00eanI"]}, {"bbox": [75, 1408, 1408, 1440], "words": [{"bbox": [75, 1415, 146, 1440], "text": "Rapid"}, {"bbox": [154, 1415, 210, 1440], "text": "City,"}, {"bbox": [217, 1415, 274, 1435], "text": "Nam"}, {"bbox": [282, 1415, 369, 1435], "text": "Dakota"}, {"bbox": [377, 1415, 456, 1435], "text": "Vratsa"}, {"bbox": [464, 1412, 526, 1440], "text": "(t\u1ec9nh)"}, {"bbox": [534, 1415, 589, 1435], "text": "New"}, {"bbox": [597, 1420, 651, 1440], "text": "prog"}, {"bbox": [659, 1415, 707, 1435], "text": "Pho"}, {"bbox": [715, 1415, 768, 1435], "text": "m\u00e1t:"}, {"bbox": [776, 1415, 841, 1440], "text": "Ng\u00e2n"}, {"bbox": [849, 1415, 909, 1440], "text": "h\u00e0ng"}, {"bbox": [916, 1415, 992, 1435], "text": "Anh\u2014"}, {"bbox": [1000, 1415, 1053, 1439], "text": "Lu\u1eadt"}, {"bbox": [1061, 1415, 1125, 1435], "text": "Gi\u00e1m"}, {"bbox": [1133, 1415, 1170, 1435], "text": "s\u00e1t"}, {"bbox": [1178, 1408, 1212, 1440], "text": "\u1ee6y"}, {"bbox": [1220, 1415, 1265, 1435], "text": "ban"}, {"bbox": [1273, 1415, 1362, 1440], "text": "th\u01b0\u1eddng"}, {"bbox": [1370, 1420, 1399, 1439], "text": "v\u1ee5"}, {"bbox": [1407, 1410, 1407, 1410], "text": ""}], "texts": ["Rapid", "City,", "Nam", "Dakota", "Vratsa", "(t\u1ec9nh)", "New", "prog", "Pho", "m\u00e1t:", "Ng\u00e2n", "h\u00e0ng", "Anh\u2014", "Lu\u1eadt", "Gi\u00e1m", "s\u00e1t", "\u1ee6y", "ban", "th\u01b0\u1eddng", "v\u1ee5", ""]}, {"bbox": [75, 1444, 1423, 1474], "words": [{"bbox": [75, 1449, 202, 1469], "text": "CristoforoI"}, {"bbox": [210, 1449, 326, 1473], "text": "Colombo,"}, {"bbox": [334, 1449, 399, 1469], "text": "Danh"}, {"bbox": [407, 1449, 465, 1469], "text": "s\u00e1ch"}, {"bbox": [473, 1449, 516, 1469], "text": "c\u00e1c"}, {"bbox": [524, 1449, 589, 1469], "text": "n\u01b0\u1edbc"}, {"bbox": [597, 1449, 656, 1469], "text": "ch\u00e2u"}, {"bbox": [664, 1449, 703, 1469], "text": "Phi"}, {"bbox": [711, 1449, 764, 1469], "text": "theo"}, {"bbox": [772, 1449, 817, 1473], "text": "m\u1eadt"}, {"bbox": [825, 1449, 861, 1473], "text": "\u0111\u1ed9l"}, {"bbox": [869, 1449, 914, 1469], "text": "d\u00e2n"}, {"bbox": [922, 1444, 951, 1469], "text": "s\u1ed1"}, {"bbox": [959, 1449, 1036, 1469], "text": "Th\u00e1nh"}, {"bbox": [1044, 1445, 1065, 1469], "text": "l\u1ec5"}, {"bbox": [1073, 1449, 1185, 1469], "text": "Endoclita"}, {"bbox": [1193, 1449, 1279, 1469], "text": "Volata-"}, {"bbox": [1286, 1449, 1368, 1474], "text": "Liberty"}, {"bbox": [1376, 1449, 1422, 1469], "text": "Inte"}], "texts": ["CristoforoI", "Colombo,", "Danh", "s\u00e1ch", "c\u00e1c", "n\u01b0\u1edbc", "ch\u00e2u", "Phi", "theo", "m\u1eadt", "\u0111\u1ed9l", "d\u00e2n", "s\u1ed1", "Th\u00e1nh", "l\u1ec5", "Endoclita", "Volata-", "Liberty", "Inte"]}, {"bbox": [74, 1477, 1417, 1507], "words": [{"bbox": [74, 1482, 101, 1502], "text": "A."}, {"bbox": [109, 1482, 134, 1502], "text": "T."}, {"bbox": [141, 1482, 203, 1502], "text": "Price"}, {"bbox": [211, 1482, 275, 1506], "text": "Nh\u1ea1c"}, {"bbox": [283, 1482, 387, 1502], "text": "ambient!"}, {"bbox": [395, 1477, 467, 1507], "text": "Gi\u1ed1ng"}, {"bbox": [475, 1482, 517, 1502], "text": "lo\u00e0i"}, {"bbox": [525, 1482, 574, 1502], "text": "C\u00e1c"}, {"bbox": [582, 1482, 627, 1502], "text": "d\u00e2n"}, {"bbox": [635, 1482, 672, 1506], "text": "t\u1ed9c"}, {"bbox": [680, 1482, 777, 1502], "text": "German"}, {"bbox": [785, 1482, 869, 1507], "text": "V\u01b0\u01a1ng"}, {"bbox": [877, 1477, 936, 1507], "text": "qu\u1ed1c"}, {"bbox": [944, 1482, 979, 1502], "text": "H\u00e0"}, {"bbox": [987, 1482, 1032, 1502], "text": "Lan"}, {"bbox": [1040, 1482, 1114, 1502], "text": "Nauru"}, {"bbox": [1122, 1482, 1233, 1507], "text": "Kronberg"}, {"bbox": [1240, 1482, 1265, 1502], "text": "Ai"}, {"bbox": [1273, 1477, 1302, 1502], "text": "v\u1ec1"}, {"bbox": [1310, 1482, 1364, 1502], "text": "Kinh"}, {"bbox": [1372, 1477, 1416, 1502], "text": "b\u1eafc"}], "texts": ["A.", "T.", "Price", "Nh\u1ea1c", "ambient!", "Gi\u1ed1ng", "lo\u00e0i", "C\u00e1c", "d\u00e2n", "t\u1ed9c", "German", "V\u01b0\u01a1ng", "qu\u1ed1c", "H\u00e0", "Lan", "Nauru", "Kronberg", "Ai", "v\u1ec1", "Kinh", "b\u1eafc"]}, {"bbox": [75, 1511, 1425, 1541], "words": [{"bbox": [75, 1516, 145, 1536], "text": "David"}, {"bbox": [153, 1516, 245, 1536], "text": "Edward"}, {"bbox": [253, 1516, 379, 1541], "text": "Hughes-:1"}, {"bbox": [387, 1516, 583, 1540], "text": "Salesforce.com;"}, {"bbox": [591, 1516, 638, 1540], "text": "B\u1ea1c"}, {"bbox": [646, 1516, 697, 1536], "text": "Li\u00eau"}, {"bbox": [705, 1516, 782, 1541], "text": "(th\u00e0nh"}, {"bbox": [790, 1511, 844, 1541], "text": "ph\u1ed1)"}, {"bbox": [851, 1516, 998, 1541], "text": "Ajatashatru,"}, {"bbox": [1006, 1516, 1074, 1536], "text": "1992!"}, {"bbox": [1082, 1516, 1120, 1536], "text": "US"}, {"bbox": [1128, 1516, 1194, 1541], "text": "Open"}, {"bbox": [1202, 1528, 1211, 1536], "text": "-"}, {"bbox": [1219, 1516, 1290, 1536], "text": "Men's"}, {"bbox": [1298, 1516, 1396, 1541], "text": "Singles-"}, {"bbox": [1404, 1516, 1425, 1536], "text": "G"}], "texts": ["David", "Edward", "Hughes-:1", "Salesforce.com;", "B\u1ea1c", "Li\u00eau", "(th\u00e0nh", "ph\u1ed1)", "Ajatashatru,", "1992!", "US", "Open", "-", "Men's", "Singles-", "G"]}, {"bbox": [75, 1543, 1423, 1575], "words": [{"bbox": [75, 1545, 131, 1570], "text": "Tr\u1ea7n"}, {"bbox": [138, 1550, 206, 1575], "text": "H\u01b0ng"}, {"bbox": [213, 1550, 272, 1574], "text": "\u0110\u1ea1o:"}, {"bbox": [280, 1550, 343, 1575], "text": "B\u00f3ng"}, {"bbox": [351, 1543, 375, 1570], "text": "r\u1ed5"}, {"bbox": [383, 1550, 436, 1570], "text": "3x3-"}, {"bbox": [444, 1545, 500, 1570], "text": "Tr\u1ea7n"}, {"bbox": [508, 1545, 543, 1570], "text": "C\u1ed1"}, {"bbox": [551, 1550, 643, 1575], "text": "Worley,"}, {"bbox": [651, 1550, 719, 1570], "text": "Idaho"}, {"bbox": [727, 1550, 775, 1570], "text": "Sao"}, {"bbox": [783, 1547, 824, 1570], "text": "H\u1ea3i"}, {"bbox": [832, 1550, 931, 1575], "text": "V\u01b0\u01a1ng?"}, {"bbox": [939, 1550, 987, 1570], "text": "V\u0103n"}, {"bbox": [995, 1550, 1070, 1575], "text": "ph\u00f2ng"}, {"bbox": [1078, 1550, 1151, 1570], "text": "Ch\u00ednh"}, {"bbox": [1159, 1547, 1204, 1575], "text": "ph\u1ee7"}, {"bbox": [1212, 1550, 1268, 1575], "text": "(Vi\u1ec7t"}, {"bbox": [1276, 1550, 1350, 1575], "text": "Nam)."}, {"bbox": [1358, 1550, 1422, 1570], "text": "Dubs"}], "texts": ["Tr\u1ea7n", "H\u01b0ng", "\u0110\u1ea1o:", "B\u00f3ng", "r\u1ed5", "3x3-", "Tr\u1ea7n", "C\u1ed1", "Worley,", "Idaho", "Sao", "H\u1ea3i", "V\u01b0\u01a1ng?", "V\u0103n", "ph\u00f2ng", "Ch\u00ednh", "ph\u1ee7", "(Vi\u1ec7t", "Nam).", "Dubs"]}, {"bbox": [75, 1578, 204, 1608], "words": [{"bbox": [75, 1578, 122, 1603], "text": "Th\u1ebf"}, {"bbox": [130, 1580, 158, 1608], "text": "k\u1ef7"}, {"bbox": [166, 1583, 204, 1603], "text": "10."}], "texts": ["Th\u1ebf k\u1ef7 10"]}], "bbox": [75, 1310, 1425, 1612]}, {"component": "paragraph", "lines": [{"bbox": [75, 1614, 1411, 1646], "words": [{"bbox": [75, 1621, 167, 1646], "text": "Th\u00f4ng1"}, {"bbox": [175, 1621, 261, 1646], "text": "D\u01b0\u01a1ng"}, {"bbox": [269, 1621, 317, 1645], "text": "V\u1eadn"}, {"bbox": [325, 1621, 366, 1641], "text": "H\u00e0i"}, {"bbox": [374, 1621, 424, 1641], "text": "C\u00e2u"}, {"bbox": [432, 1621, 467, 1645], "text": "l\u1ea1c"}, {"bbox": [475, 1621, 505, 1645], "text": "b\u1ed9"}, {"bbox": [513, 1621, 573, 1646], "text": "b\u00f3ng"}, {"bbox": [581, 1621, 611, 1641], "text": "\u0111\u00e1"}, {"bbox": [619, 1621, 679, 1646], "text": "Long"}, {"bbox": [686, 1621, 720, 1641], "text": "An"}, {"bbox": [728, 1621, 775, 1645], "text": "Vi\u1ec7t"}, {"bbox": [783, 1621, 840, 1641], "text": "Nam"}, {"bbox": [848, 1621, 877, 1645], "text": "t\u1ea1i"}, {"bbox": [885, 1616, 932, 1641], "text": "Th\u1ebf"}, {"bbox": [940, 1621, 984, 1645], "text": "v\u1eadn"}, {"bbox": [992, 1621, 1028, 1645], "text": "h\u1ed9i"}, {"bbox": [1036, 1621, 1088, 1641], "text": "M\u00f9a"}, {"bbox": [1096, 1621, 1126, 1641], "text": "h\u00e8"}, {"bbox": [1134, 1621, 1194, 1641], "text": "2008"}, {"bbox": [1202, 1621, 1264, 1641], "text": "Todd"}, {"bbox": [1271, 1621, 1370, 1641], "text": "Lodwick"}, {"bbox": [1378, 1614, 1410, 1641], "text": "T\u1ed5"}], "texts": ["Th\u00f4ng1", "D\u01b0\u01a1ng", "V\u1eadn", "H\u00e0i", "C\u00e2u", "l\u1ea1c", "b\u1ed9", "b\u00f3ng", "\u0111\u00e1", "Long", "An", "Vi\u1ec7t", "Nam", "t\u1ea1i", "Th\u1ebf", "v\u1eadn", "h\u1ed9i", "M\u00f9a", "h\u00e8", "2008", "Todd", "Lodwick", "T\u1ed5"]}, {"bbox": [75, 1648, 1420, 1680], "words": [{"bbox": [75, 1655, 119, 1675], "text": "Joe"}, {"bbox": [127, 1655, 231, 1675], "text": "Kraemer"}, {"bbox": [238, 1655, 375, 1680], "text": "(composer)"}, {"bbox": [383, 1655, 481, 1680], "text": "Tr\u01b0\u1eddngl"}, {"bbox": [488, 1655, 538, 1675], "text": "Cao"}, {"bbox": [546, 1648, 606, 1680], "text": "\u0111\u1eb3ng"}, {"bbox": [614, 1650, 674, 1680], "text": "ngh\u1ec1"}, {"bbox": [682, 1650, 735, 1675], "text": "Ti\u1ec1n"}, {"bbox": [743, 1655, 815, 1680], "text": "Giang"}, {"bbox": [823, 1650, 888, 1677], "text": "Qu\u1ed1c"}, {"bbox": [896, 1655, 917, 1679], "text": "l\u1ed9"}, {"bbox": [925, 1655, 955, 1675], "text": "26"}, {"bbox": [963, 1655, 1022, 1680], "text": "(H\u00e0n"}, {"bbox": [1030, 1650, 1113, 1680], "text": "Qu\u1ed1c)-"}, {"bbox": [1121, 1655, 1181, 1675], "text": "1984"}, {"bbox": [1189, 1655, 1267, 1675], "text": "Novak"}, {"bbox": [1275, 1655, 1379, 1680], "text": "Djokovic"}, {"bbox": [1387, 1655, 1419, 1675], "text": "Fo"}], "texts": ["Joe", "Kraemer", "(composer)", "Tr\u01b0\u1eddngl", "Cao", "\u0111\u1eb3ng", "ngh\u1ec1", "Ti\u1ec1n", "Giang", "Qu\u1ed1c", "l\u1ed9", "26", "(H\u00e0n", "Qu\u1ed1c)-", "1984", "Novak", "Djokovic", "Fo"]}, {"bbox": [75, 1682, 1421, 1714], "words": [{"bbox": [75, 1689, 140, 1709], "text": "Danh"}, {"bbox": [148, 1689, 206, 1709], "text": "s\u00e1ch"}, {"bbox": [214, 1684, 258, 1709], "text": "c\u1ea7u"}, {"bbox": [266, 1686, 304, 1709], "text": "th\u1ee7"}, {"bbox": [312, 1689, 378, 1709], "text": "thami"}, {"bbox": [386, 1689, 419, 1713], "text": "d\u1ef1"}, {"bbox": [427, 1686, 475, 1709], "text": "Gi\u1ea3i"}, {"bbox": [483, 1689, 512, 1709], "text": "v\u00f4"}, {"bbox": [520, 1689, 570, 1713], "text": "\u0111\u1ecbch"}, {"bbox": [578, 1689, 638, 1714], "text": "b\u00f3ng"}, {"bbox": [646, 1689, 676, 1709], "text": "\u0111\u00e1"}, {"bbox": [684, 1684, 722, 1709], "text": "th\u1ebf"}, {"bbox": [730, 1689, 775, 1714], "text": "gi\u1edbi"}, {"bbox": [783, 1689, 870, 1709], "text": "1954\u2014"}, {"bbox": [878, 1684, 939, 1709], "text": "Thi\u1ebft"}, {"bbox": [947, 1689, 968, 1713], "text": "b\u1ecb"}, {"bbox": [976, 1689, 1037, 1713], "text": "th\u1ef1ci"}, {"bbox": [1045, 1684, 1068, 1709], "text": "t\u1ebf"}, {"bbox": [1076, 1686, 1106, 1709], "text": "\u1ea3o"}, {"bbox": [1114, 1689, 1192, 1714], "text": "Kh\u00e1ng"}, {"bbox": [1200, 1682, 1238, 1709], "text": "th\u1ec3"}, {"bbox": [1246, 1689, 1294, 1709], "text": "\u0111\u01a1n"}, {"bbox": [1302, 1689, 1370, 1714], "text": "d\u00f2ng,"}, {"bbox": [1378, 1689, 1421, 1709], "text": "Ser"}], "texts": ["Danh", "s\u00e1ch", "c\u1ea7u", "th\u1ee7", "thami", "d\u1ef1", "Gi\u1ea3i", "v\u00f4", "\u0111\u1ecbch", "b\u00f3ng", "\u0111\u00e1", "th\u1ebf", "gi\u1edbi", "1954\u2014", "Thi\u1ebft", "b\u1ecb", "th\u1ef1ci", "t\u1ebf", "\u1ea3o", "Kh\u00e1ng", "th\u1ec3", "\u0111\u01a1n", "d\u00f2ng,", "Ser"]}, {"bbox": [75, 1716, 1414, 1748], "words": [{"bbox": [75, 1723, 182, 1748], "text": "England;"}, {"bbox": [190, 1723, 244, 1743], "text": "L\u1eddi1"}, {"bbox": [252, 1723, 288, 1743], "text": "n\u00f3i"}, {"bbox": [296, 1723, 356, 1748], "text": "b\u00e1ng"}, {"bbox": [364, 1716, 402, 1743], "text": "b\u1ed5I"}, {"bbox": [410, 1720, 491, 1748], "text": "Qu\u1ea3ng"}, {"bbox": [499, 1723, 569, 1747], "text": "B\u00ecnh;i"}, {"bbox": [576, 1723, 670, 1743], "text": "Android"}, {"bbox": [678, 1723, 766, 1748], "text": "Nougat"}, {"bbox": [774, 1716, 827, 1743], "text": "Ti\u1ec3u"}, {"bbox": [834, 1718, 893, 1748], "text": "qu\u1ed1c"}, {"bbox": [901, 1723, 969, 1743], "text": "Jarai-"}, {"bbox": [977, 1723, 1024, 1743], "text": "Iran"}, {"bbox": [1032, 1723, 1095, 1748], "text": "B\u00f3ng"}, {"bbox": [1103, 1723, 1172, 1748], "text": "(b\u00f3ng"}, {"bbox": [1180, 1723, 1219, 1748], "text": "\u0111\u00e1)"}, {"bbox": [1227, 1723, 1281, 1743], "text": "T\u00edch"}, {"bbox": [1289, 1723, 1334, 1747], "text": "b\u1ec7n"}, {"bbox": [1342, 1723, 1413, 1743], "text": "Kimbr"}], "texts": ["England;", "L\u1eddi1", "n\u00f3i", "b\u00e1ng", "b\u1ed5I", "Qu\u1ea3ng", "B\u00ecnh;i", "Android", "Nougat", "Ti\u1ec3u", "qu\u1ed1c", "Jarai-", "Iran", "B\u00f3ng", "(b\u00f3ng", "\u0111\u00e1)", "T\u00edch", "b\u1ec7n", "Kimbr"]}, {"bbox": [74, 1751, 1419, 1783], "words": [{"bbox": [74, 1758, 116, 1782], "text": "\u0110\u1ed9i"}, {"bbox": [124, 1751, 191, 1783], "text": "tuy\u1ec3n"}, {"bbox": [199, 1758, 259, 1783], "text": "b\u00f3ng"}, {"bbox": [267, 1758, 297, 1778], "text": "\u0111\u00e1"}, {"bbox": [305, 1753, 364, 1783], "text": "qu\u1ed1c"}, {"bbox": [372, 1758, 408, 1783], "text": "gia"}, {"bbox": [416, 1758, 463, 1782], "text": "Vi\u1ec7t"}, {"bbox": [471, 1758, 528, 1778], "text": "Nam"}, {"bbox": [536, 1758, 586, 1778], "text": "D\u00e2n"}, {"bbox": [594, 1755, 638, 1778], "text": "ch\u1ee7"}, {"bbox": [646, 1758, 711, 1783], "text": "C\u1ed9ng"}, {"bbox": [719, 1758, 772, 1782], "text": "h\u00f2a,"}, {"bbox": [780, 1758, 846, 1778], "text": "1929l"}, {"bbox": [854, 1758, 927, 1778], "text": "Ho\u00e0n!"}, {"bbox": [935, 1758, 974, 1778], "text": "l\u01b0u"}, {"bbox": [982, 1753, 1029, 1778], "text": "B\u1eafc"}, {"bbox": [1036, 1758, 1078, 1782], "text": "\u0110\u1ea1i"}, {"bbox": [1086, 1758, 1132, 1783], "text": "T\u00e2y"}, {"bbox": [1140, 1758, 1226, 1783], "text": "D\u01b0\u01a1ng"}, {"bbox": [1234, 1758, 1303, 1783], "text": "B\u00f3ngi"}, {"bbox": [1311, 1758, 1341, 1778], "text": "\u0111\u00e1"}, {"bbox": [1349, 1758, 1419, 1783], "text": "trong."}], "texts": ["\u0110\u1ed9i", "tuy\u1ec3n", "b\u00f3ng", "\u0111\u00e1", "qu\u1ed1c", "gia", "Vi\u1ec7t", "Nam", "D\u00e2n", "ch\u1ee7", "C\u1ed9ng", "h\u00f2a,", "1929l", "Ho\u00e0n!", "l\u01b0u", "B\u1eafc", "\u0110\u1ea1i", "T\u00e2y", "D\u01b0\u01a1ng", "B\u00f3ngi", "\u0111\u00e1", "trong."]}, {"bbox": [75, 1785, 1410, 1817], "words": [{"bbox": [75, 1792, 125, 1817], "text": "Nga"}, {"bbox": [133, 1792, 200, 1812], "text": "Kokki"}, {"bbox": [208, 1792, 309, 1812], "text": "Ronaldo"}, {"bbox": [317, 1787, 385, 1817], "text": "Ti\u1ebfng"}, {"bbox": [392, 1792, 444, 1812], "text": "M\u00e2n"}, {"bbox": [452, 1792, 498, 1812], "text": "Kim"}, {"bbox": [506, 1792, 562, 1812], "text": "Dinh"}, {"bbox": [570, 1792, 620, 1816], "text": "H\u1eadu"}, {"bbox": [628, 1792, 662, 1817], "text": "k\u1ef3l"}, {"bbox": [670, 1792, 738, 1817], "text": "trungi"}, {"bbox": [746, 1785, 781, 1812], "text": "c\u1ed5l"}, {"bbox": [789, 1792, 865, 1817], "text": "Tuy\u00ean"}, {"bbox": [873, 1792, 960, 1817], "text": "Quangl"}, {"bbox": [968, 1792, 1051, 1817], "text": "(th\u00e0nhi"}, {"bbox": [1059, 1787, 1113, 1817], "text": "ph\u1ed1)"}, {"bbox": [1121, 1792, 1156, 1812], "text": "Do"}, {"bbox": [1164, 1792, 1225, 1812], "text": "Th\u00e1i!"}, {"bbox": [1233, 1792, 1284, 1817], "text": "gi\u00e1o"}, {"bbox": [1292, 1787, 1341, 1817], "text": "C\u1ea5y"}, {"bbox": [1349, 1792, 1409, 1817], "text": "gh\u00e9p"}], "texts": ["Nga", "Kokki", "Ronaldo", "Ti\u1ebfng", "M\u00e2n", "Kim", "Dinh", "H\u1eadu", "k\u1ef3l", "trungi", "c\u1ed5l", "Tuy\u00ean", "Quangl", "(th\u00e0nhi", "ph\u1ed1)", "Do", "Th\u00e1i!", "gi\u00e1o", "C\u1ea5y", "gh\u00e9p"]}, {"bbox": [75, 1826, 246, 1851], "words": [{"bbox": [75, 1826, 160, 1846], "text": "Natalie"}, {"bbox": [168, 1826, 246, 1851], "text": "Fryde."}], "texts": ["Natalie Fryde"]}], "bbox": [75, 1616, 1425, 1856]}], "bbox": [0, 0, 1500, 2000], "text": ["Th\u00f4ng1", "D\u01b0\u01a1ng", "V\u1eadn", "H\u00e0i", "C\u00e2u", "l\u1ea1c", "b\u1ed9", "b\u00f3ng", "\u0111\u00e1", "Long", "An", "Vi\u1ec7t", "Nam", "t\u1ea1i", "Th\u1ebf", "v\u1eadn", "h\u1ed9i", "M\u00f9a", "h\u00e8", "2008", "Todd", "Lodwick", "T\u1ed5", "Joe", "Kraemer", "(composer)", "Tr\u01b0\u1eddngl", "Cao", "\u0111\u1eb3ng", "ngh\u1ec1", "Ti\u1ec1n", "Giang", "Qu\u1ed1c", "l\u1ed9", "26", "(H\u00e0n", "Qu\u1ed1c)-", "1984", "Novak", "Djokovic", "Fo", "Danh", "s\u00e1ch", "c\u1ea7u", "th\u1ee7", "thami", "d\u1ef1", "Gi\u1ea3i", "v\u00f4", "\u0111\u1ecbch", "b\u00f3ng", "\u0111\u00e1", "th\u1ebf", "gi\u1edbi", "1954\u2014", "Thi\u1ebft", "b\u1ecb", "th\u1ef1ci", "t\u1ebf", "\u1ea3o", "Kh\u00e1ng", "th\u1ec3", "\u0111\u01a1n", "d\u00f2ng,", "Ser", "England;", "L\u1eddi1", "n\u00f3i", "b\u00e1ng", "b\u1ed5I", "Qu\u1ea3ng", "B\u00ecnh;i", "Android", "Nougat", "Ti\u1ec3u", "qu\u1ed1c", "Jarai-", "Iran", "B\u00f3ng", "(b\u00f3ng", "\u0111\u00e1)", "T\u00edch", "b\u1ec7n", "Kimbr", "\u0110\u1ed9i", "tuy\u1ec3n", "b\u00f3ng", "\u0111\u00e1", "qu\u1ed1c", "gia", "Vi\u1ec7t", "Nam", "D\u00e2n", "ch\u1ee7", "C\u1ed9ng", "h\u00f2a,", "1929l", "Ho\u00e0n!", "l\u01b0u", "B\u1eafc", "\u0110\u1ea1i", "T\u00e2y", "D\u01b0\u01a1ng", "B\u00f3ngi", "\u0111\u00e1", "trong.", "Nga", "Kokki", "Ronaldo", "Ti\u1ebfng", "M\u00e2n", "Kim", "Dinh", "H\u1eadu", "k\u1ef3l", "trungi", "c\u1ed5l", "Tuy\u00ean", "Quangl", "(th\u00e0nhi", "ph\u1ed1)", "Do", "Th\u00e1i!", "gi\u00e1o", "C\u1ea5y", "gh\u00e9p", "Natalie Fryde"]}